pydevlpr/__init__.py
pydevlpr/DevlprClient.py
pydevlpr/DevlprServer.py
pydevlpr/main.py
pydevlpr/py.typed
pydevlpr/typing.py
pydevlpr-0.3.1.dist-info/LICENSE
pydevlpr-0.3.1.dist-info/WHEEL
pydevlpr-0.3.1.dist-info/METADATA
pydevlpr-0.3.1.dist-info/RECORD
