Metadata-Version: 2.1
Name: pydevlpr
Version: 0.3.1
Summary: Frontend for connecting to devlprd and processing data from a FANTM DEVLPR
Home-page: https://github.com/FANTM/pydevlpr
License: MIT
Author: Ezra Boley
Author-email: hello@getfantm.com
Requires-Python: >=3.7,<3.11
Classifier: License :: OSI Approved :: MIT License
Classifier: Programming Language :: Python :: 3
Classifier: Programming Language :: Python :: 3.7
Classifier: Programming Language :: Python :: 3.8
Classifier: Programming Language :: Python :: 3.9
Requires-Dist: devlprd (>=0.4.2)
Requires-Dist: pydevlpr-protocol (>=0.1.0)
Project-URL: Documentation, https://docs.getfantm.com
Project-URL: Repository, https://github.com/FANTM/pydevlpr
